raceknn/__init__.py
raceknn/raceknn.py
raceknn-0.1.1.dist-info/licenses/LICENSE.txt
raceknn-0.1.1.dist-info/METADATA
raceknn-0.1.1.dist-info/WHEEL
raceknn-0.1.1.dist-info/top_level.txt
raceknn-0.1.1.dist-info/RECORD
