Metadata-Version: 2.4
Name: raceknn
Version: 0.1.1
Summary: A hybrid rule-guided k-Nearest Neighbor classifier for improved performance.
Author: Mahdiyeh Ebrahimi
Project-URL: Homepage, https://github.com/mahdiyehebrahimi/RACEkNN
Project-URL: Bug Tracker, https://github.com/mahdiyehebrahimi/RACEkNN/issues
Project-URL: Original Paper, https://doi.org/10.1016/j.knosys.2024.112357
Keywords: knn,k-nearest-neighbors,rule-based,classification,machine learning
Classifier: Programming Language :: Python :: 3
Classifier: License :: OSI Approved :: MIT License
Classifier: Operating System :: OS Independent
Classifier: Intended Audience :: Science/Research
Classifier: Topic :: Scientific/Engineering :: Artificial Intelligence
Requires-Python: >=3.7
License-File: LICENSE.txt
Requires-Dist: numpy
Requires-Dist: pandas
Requires-Dist: scikit-learn
Requires-Dist: optbinning
Dynamic: license-file
